fast_svmlight_loader-0.1a2.data/purelib/fast_svmlight_loader/__init__.py
fast_svmlight_loader-0.1a2.data/purelib/fast_svmlight_loader/compat.py
fast_svmlight_loader-0.1a2.data/purelib/fast_svmlight_loader/core.py
fast_svmlight_loader-0.1a2.data/purelib/fast_svmlight_loader/libfast_svmlight_loader.so
fast_svmlight_loader-0.1a2.data/purelib/fast_svmlight_loader/libpath.py
fast_svmlight_loader-0.1a2.dist-info/DESCRIPTION.rst
fast_svmlight_loader-0.1a2.dist-info/METADATA
fast_svmlight_loader-0.1a2.dist-info/RECORD
fast_svmlight_loader-0.1a2.dist-info/WHEEL
fast_svmlight_loader-0.1a2.dist-info/metadata.json
fast_svmlight_loader-0.1a2.dist-info/top_level.txt
