Metadata-Version: 2.0
Name: fast-svmlight-loader
Version: 0.1a2
Summary: fast_svmlight_loader: fast reader for SVMLight file
Home-page: https://github.com/hcho3/fast_svmlight_loader
Author: Philip Cho
Author-email: chohyu01@cs.washington.edu
License: UNKNOWN
Platform: UNKNOWN
